{"name":"Aselle Hbarbarian","displayName":"Aselle Hbarbarian #01252","description":"Aselle of Hbarbarian Club","serial":1252,"assetCID":"bafybeiahkar23325zwq7mlyyzahb5ve525ndqebbr4aulptw6kheewy5ea","metadataCID":"bafkreihhblgfayvoulahvjednbfb4zxgz5o5fixh5dwzwnbs2trsfek7wa","rarity":947.04168,"rank":9529,"traits":[{"name":"background","value":"Ostry gradient background","occurrences":"174 (1.74%)","score":"57.47126"},{"name":"back","value":"None","occurrences":"0 (0%)","score":0},{"name":"body","value":"Brown skin with hair","occurrences":"1416 (14.16%)","score":"14.12429"},{"name":"tattoo","value":"None","occurrences":"0 (0%)","score":0},{"name":"mouth","value":"Normal","occurrences":"0 (0%)","score":0},{"name":"nose","value":"Roseapple nose","occurrences":"782 (7.82%)","score":"25.57545"},{"name":"armor","value":"Half metlu armor","occurrences":"282 (2.82%)","score":"177.30496"},{"name":"chestband","value":"None","occurrences":"0 (0%)","score":0},{"name":"necklace","value":"None","occurrences":"0 (0%)","score":0},{"name":"wristband","value":"Five cut wristband","occurrences":"431 (4.31%)","score":"69.60557"},{"name":"ears","value":"Bat ears with a cut ring ","occurrences":"362 (3.62%)","score":"55.24862"},{"name":"eyes","value":"Side eyes","occurrences":"667 (6.67%)","score":"44.97751"},{"name":"sunglasses","value":"None","occurrences":"0 (0%)","score":0},{"name":"beard","value":"White beard","occurrences":"430 (4.3%)","score":"93.02326"},{"name":"hair","value":"Normal","occurrences":"0 (0%)","score":0},{"name":"helmet","value":"Iron horn threaded helmet","occurrences":"506 (5.06%)","score":"79.05138"},{"name":"antler","value":"None","occurrences":"0 (0%)","score":0},{"name":"weapon_left","value":"Big sword","occurrences":"268 (2.68%)","score":"186.56716"},{"name":"weapon_right","value":"Blue ax","occurrences":"347 (3.47%)","score":"144.09222"}]}