{"name":"Ewahla Hbarbarian","displayName":"Ewahla Hbarbarian #01326","description":"Ewahla of Hbarbarian Club","serial":1326,"assetCID":"bafybeidqfsz4mc5wauzuh5jsagjjq6c4hlfqde5rswaabbv67d47bsua6u","metadataCID":"bafkreia4b5vvvho3knfegayvj7zxalcgdlw3q5ghoo4bfj2xamilfis2om","rarity":1382.00435,"rank":4930,"traits":[{"name":"background","value":"Gradient moon gradient background","occurrences":"266 (2.66%)","score":"37.59398"},{"name":"back","value":"Logan sword back","occurrences":"252 (2.52%)","score":"119.04762"},{"name":"body","value":"White skin clear body","occurrences":"3588 (35.88%)","score":"5.57414"},{"name":"tattoo","value":"None","occurrences":"0 (0%)","score":0},{"name":"mouth","value":"Normal","occurrences":"0 (0%)","score":0},{"name":"nose","value":"Nose with red ring","occurrences":"1655 (16.55%)","score":"12.08459"},{"name":"armor","value":"Half metlu armor","occurrences":"282 (2.82%)","score":"177.30496"},{"name":"chestband","value":"None","occurrences":"0 (0%)","score":0},{"name":"necklace","value":"None","occurrences":"0 (0%)","score":0},{"name":"wristband","value":"None","occurrences":"0 (0%)","score":0},{"name":"ears","value":"Byzn ears with a red f ring","occurrences":"730 (7.3%)","score":"27.39726"},{"name":"eyes","value":"Side eyes","occurrences":"667 (6.67%)","score":"44.97751"},{"name":"sunglasses","value":"None","occurrences":"0 (0%)","score":0},{"name":"beard","value":"Lbrown beard","occurrences":"680 (6.8%)","score":"58.82353"},{"name":"hair","value":"Tinto lbrown hair","occurrences":"242 (2.42%)","score":"165.28926"},{"name":"helmet","value":"None","occurrences":"0 (0%)","score":0},{"name":"antler","value":"Green hug antler","occurrences":"98 (0.98%)","score":"408.16327"},{"name":"weapon_left","value":"Horn blade","occurrences":"274 (2.74%)","score":"182.48175"},{"name":"weapon_right","value":"Twin ax","occurrences":"349 (3.49%)","score":"143.26648"}]}