{"name":"Fanalan Hbarbarian","displayName":"Fanalan Hbarbarian #01396","description":"Fanalan of Hbarbarian Club","serial":1396,"assetCID":"bafybeihbktspa7h7ma2rnznoegj2rym2hlax5s3csn5dkn6fvweqjeqyja","metadataCID":"bafkreieqliouvylttwdad33vu5l53txy3sc3yfe5onpkwpw6ogyykb3zem","rarity":22.82008,"rank":4796,"traits":[{"name":"background","value":"Bambo gradient background","occurrences":"251 (2.51%)","score":39.8406374501992},{"name":"back","value":"None","occurrences":"0 (0%)","score":0},{"name":"body","value":"White skin with hair","occurrences":"1465 (14.65%)","score":6.825938566552901},{"name":"tattoo","value":"Brown dragon tattoo","occurrences":"224 (2.24%)","score":44.642857142857146},{"name":"mouth","value":"Normal","occurrences":"0 (0%)","score":0},{"name":"nose","value":"Bull's nose","occurrences":"826 (8.26%)","score":12.106537530266344},{"name":"armor","value":"None","occurrences":"0 (0%)","score":0},{"name":"chestband","value":"None","occurrences":"0 (0%)","score":0},{"name":"necklace","value":"Ring lock necklace","occurrences":"143 (1.43%)","score":69.93006993006993},{"name":"wristband","value":"Prince wristband","occurrences":"355 (3.55%)","score":28.169014084507044},{"name":"ears","value":"S cut ears with a anchor ring","occurrences":"695 (6.95%)","score":14.388489208633093},{"name":"eyes","value":"Super angry eyes","occurrences":"683 (6.83%)","score":14.641288433382138},{"name":"sunglasses","value":"Flower frame sunglasses","occurrences":"189 (1.89%)","score":52.91005291005291},{"name":"beard","value":"Twinbrow beard","occurrences":"278 (2.78%)","score":35.97122302158273},{"name":"hair","value":"Normal","occurrences":"0 (0%)","score":0},{"name":"helmet","value":"Orange horn lock helmet","occurrences":"652 (6.52%)","score":15.337423312883436},{"name":"antler","value":"None","occurrences":"0 (0%)","score":0},{"name":"weapon_left","value":"Bull's sword","occurrences":"315 (3.15%)","score":31.746031746031747},{"name":"weapon_right","value":"Killer ax","occurrences":"172 (1.72%)","score":58.13953488372093}]}