{"name":"Wisule Hbarbarian","displayName":"Wisule Hbarbarian #01590","description":"Wisule of Hbarbarian Club","serial":1590,"assetCID":"bafybeieqlvr45u3heizpnzjnzeo7nv3owhcyiyzelyd4d5e54iwexnyely","metadataCID":"bafkreiclgdfz65tdsq3zja4poqnrz5j4nlpb3kvtereyw4p44q64lmygfu","rarity":23.34934,"rank":4413,"traits":[{"name":"background","value":"Brown ball gradient background","occurrences":"194 (1.94%)","score":51.54639175257732},{"name":"back","value":"Blue cloth back","occurrences":"235 (2.35%)","score":42.5531914893617},{"name":"body","value":"White skin clear body","occurrences":"3588 (35.88%)","score":2.787068004459309},{"name":"tattoo","value":"None","occurrences":"0 (0%)","score":0},{"name":"mouth","value":"Coco mouth","occurrences":"186 (1.86%)","score":53.763440860215056},{"name":"nose","value":"Nose with silver ring","occurrences":"1564 (15.64%)","score":6.3938618925831205},{"name":"armor","value":"Shell armor","occurrences":"373 (3.73%)","score":26.80965147453083},{"name":"chestband","value":"None","occurrences":"0 (0%)","score":0},{"name":"necklace","value":"None","occurrences":"0 (0%)","score":0},{"name":"wristband","value":"Twin bro wristband","occurrences":"225 (2.25%)","score":44.44444444444444},{"name":"ears","value":"Dwarf ears with a axe ring","occurrences":"609 (6.09%)","score":16.420361247947454},{"name":"eyes","value":"Pengy eyes","occurrences":"261 (2.61%)","score":38.31417624521073},{"name":"sunglasses","value":"None","occurrences":"0 (0%)","score":0},{"name":"beard","value":"Boxy beard","occurrences":"312 (3.12%)","score":32.05128205128205},{"name":"hair","value":"Normal","occurrences":"0 (0%)","score":0},{"name":"helmet","value":"Pop viking helmet","occurrences":"411 (4.11%)","score":24.330900243309003},{"name":"antler","value":"None","occurrences":"0 (0%)","score":0},{"name":"weapon_left","value":"Satan's blade","occurrences":"325 (3.25%)","score":30.76923076923077},{"name":"weapon_right","value":"Bull horn blade","occurrences":"154 (1.54%)","score":64.93506493506493}]}