{"name":"Nemalahn Hbarbarian","displayName":"Nemalahn Hbarbarian #02024","description":"Nemalahn of Hbarbarian Club","serial":2024,"assetCID":"bafybeiazlgqqu4pcrahao4g5qb2czvqeunsxln33su2dda64dfwzkyetza","metadataCID":"bafkreiftpejosswv2hjiq3dcnrvilafovwjuydmgx6rmekmpnknl7ke3d4","rarity":1510.20844,"rank":3523,"traits":[{"name":"background","value":"Bambo gradient background","occurrences":"251 (2.51%)","score":"39.84064"},{"name":"back","value":"Back with yellow sword","occurrences":"197 (1.97%)","score":"152.28426"},{"name":"body","value":"Brown skin with hair","occurrences":"1416 (14.16%)","score":"14.12429"},{"name":"tattoo","value":"None","occurrences":"0 (0%)","score":0},{"name":"mouth","value":"Coco mouth","occurrences":"186 (1.86%)","score":"107.52688"},{"name":"nose","value":"Rat's nose","occurrences":"1765 (17.65%)","score":"11.33144"},{"name":"armor","value":"Shell armor","occurrences":"373 (3.73%)","score":"134.04826"},{"name":"chestband","value":"None","occurrences":"0 (0%)","score":0},{"name":"necklace","value":"X necklace","occurrences":"251 (2.51%)","score":"119.52191"},{"name":"wristband","value":"None","occurrences":"0 (0%)","score":0},{"name":"ears","value":"Twin ears with s hook flip ring","occurrences":"697 (6.97%)","score":"28.69440"},{"name":"eyes","value":"Sad eyes","occurrences":"784 (7.84%)","score":"38.26531"},{"name":"sunglasses","value":"None","occurrences":"0 (0%)","score":0},{"name":"beard","value":"Twinbrow beard","occurrences":"278 (2.78%)","score":"143.88489"},{"name":"hair","value":"Red band brown hair","occurrences":"303 (3.03%)","score":"132.01320"},{"name":"helmet","value":"None","occurrences":"0 (0%)","score":0},{"name":"antler","value":"Blue dragon antler","occurrences":"239 (2.39%)","score":"167.36402"},{"name":"weapon_left","value":"Drumstick","occurrences":"213 (2.13%)","score":"234.74178"},{"name":"weapon_right","value":"Big sword","occurrences":"268 (2.68%)","score":"186.56716"}]}