{"name":"Thakulla Hbarbarian","displayName":"Thakulla Hbarbarian #02074","description":"Thakulla of Hbarbarian Club","serial":2074,"assetCID":"bafybeihxloeqbw6xdsjz2pleid7firkv6qdqwyacl3esa2vpr7ak72jarq","metadataCID":"bafkreiguiwk7awbwbdle4yv2tjoopq5mjscyxvbxjxijkgdqahw7vbghfa","rarity":2219.43773,"rank":490,"traits":[{"name":"background","value":"Light blue src gradient background","occurrences":"232 (2.32%)","score":"43.10345"},{"name":"back","value":"Big arrowhead back","occurrences":"114 (1.14%)","score":"263.15789"},{"name":"body","value":"White skin clear body","occurrences":"3588 (35.88%)","score":"5.57414"},{"name":"tattoo","value":"None","occurrences":"0 (0%)","score":0},{"name":"mouth","value":"Normal","occurrences":"0 (0%)","score":0},{"name":"nose","value":"Nose with silver ring","occurrences":"1564 (15.64%)","score":"12.78772"},{"name":"armor","value":"Ash cut armor","occurrences":"345 (3.45%)","score":"144.92754"},{"name":"chestband","value":"None","occurrences":"0 (0%)","score":0},{"name":"necklace","value":"Silver shell necklace","occurrences":"101 (1.01%)","score":"297.02970"},{"name":"wristband","value":"Orange wristband","occurrences":"158 (1.58%)","score":"189.87342"},{"name":"ears","value":"Pointy ears","occurrences":"202 (2.02%)","score":"99.00990"},{"name":"eyes","value":"Bowbro eyes","occurrences":"706 (7.06%)","score":"42.49292"},{"name":"sunglasses","value":"Bat cut sunglasses","occurrences":"64 (0.64%)","score":"468.75000"},{"name":"beard","value":"Chico beard","occurrences":"544 (5.44%)","score":"73.52941"},{"name":"hair","value":"Normal","occurrences":"0 (0%)","score":0},{"name":"helmet","value":"Red bad pyramid helmet","occurrences":"196 (1.96%)","score":"204.08163"},{"name":"antler","value":"None","occurrences":"0 (0%)","score":0},{"name":"weapon_left","value":"Twin blade","occurrences":"317 (3.17%)","score":"157.72871"},{"name":"weapon_right","value":"Hook sword","occurrences":"230 (2.3%)","score":"217.39130"}]}