{"name":"Shezife Hbarbarian","displayName":"Shezife Hbarbarian #02404","description":"Shezife of Hbarbarian Club","serial":2404,"assetCID":"bafybeickwiw7riq4umdp6ktv2z74xgepnglrurldthi2qknaeh5tv2lxey","metadataCID":"bafkreicbuj3xkmrk4t3yf5vj6mn3n7zdwtnnos62d3wjk7cuueoawa3nlq","rarity":1827.19867,"rank":1325,"traits":[{"name":"background","value":"Blue star pink gradient background","occurrences":"170 (1.7%)","score":"58.82353"},{"name":"back","value":"None","occurrences":"0 (0%)","score":0},{"name":"body","value":"White skin clear body","occurrences":"3588 (35.88%)","score":"5.57414"},{"name":"tattoo","value":"None","occurrences":"0 (0%)","score":0},{"name":"mouth","value":"Shark mouth","occurrences":"142 (1.42%)","score":"140.84507"},{"name":"nose","value":"Bull's nose","occurrences":"826 (8.26%)","score":"24.21308"},{"name":"armor","value":"Red king armor","occurrences":"349 (3.49%)","score":"143.26648"},{"name":"chestband","value":"Silwer chestband","occurrences":"56 (0.56%)","score":"535.71429"},{"name":"necklace","value":"Bad brown necklace","occurrences":"285 (2.85%)","score":"105.26316"},{"name":"wristband","value":"None","occurrences":"0 (0%)","score":0},{"name":"ears","value":"Monkey ears","occurrences":"614 (6.14%)","score":"32.57329"},{"name":"eyes","value":"Angry bird eyes","occurrences":"731 (7.31%)","score":"41.03967"},{"name":"sunglasses","value":"None","occurrences":"0 (0%)","score":0},{"name":"beard","value":"Curlyking beard","occurrences":"715 (7.15%)","score":"55.94406"},{"name":"hair","value":"Tinto lbrown hair","occurrences":"242 (2.42%)","score":"165.28926"},{"name":"helmet","value":"None","occurrences":"0 (0%)","score":0},{"name":"antler","value":"Brown long antler","occurrences":"376 (3.76%)","score":"106.38298"},{"name":"weapon_left","value":"Short pointy ax","occurrences":"313 (3.13%)","score":"159.74441"},{"name":"weapon_right","value":"Twin short blades","occurrences":"198 (1.98%)","score":"252.52525"}]}