{"name":"Kyokolleng Hbarbarian","displayName":"Kyokolleng Hbarbarian #02881","description":"Kyokolleng of Hbarbarian Club","serial":2881,"assetCID":"bafybeiatzxzdjlg63lwr7xb4mtz33spgdr3n7o7hngn4nj6ffo4znlzdme","metadataCID":"bafkreiebpub5lp47m7ijcxct3psjkdaqwlor3xh4joevaeqpz5xdwz5f44","rarity":903.78712,"rank":9719,"traits":[{"name":"background","value":"Black ash gradient background","occurrences":"250 (2.5%)","score":"40.00000"},{"name":"back","value":"None","occurrences":"0 (0%)","score":0},{"name":"body","value":"White skin with hair","occurrences":"1465 (14.65%)","score":"13.65188"},{"name":"tattoo","value":"Byzn tattoo","occurrences":"505 (5.05%)","score":"59.40594"},{"name":"mouth","value":"Normal","occurrences":"0 (0%)","score":0},{"name":"nose","value":"Nose with silver ring","occurrences":"1564 (15.64%)","score":"12.78772"},{"name":"armor","value":"None","occurrences":"0 (0%)","score":0},{"name":"chestband","value":"None","occurrences":"0 (0%)","score":0},{"name":"necklace","value":"Yenee necklace","occurrences":"215 (2.15%)","score":"139.53488"},{"name":"wristband","value":"Matyellow wristband","occurrences":"520 (5.2%)","score":"57.69231"},{"name":"ears","value":"Monkey ears twinstar rings","occurrences":"246 (2.46%)","score":"81.30081"},{"name":"eyes","value":"Crazy eyes","occurrences":"578 (5.78%)","score":"51.90311"},{"name":"sunglasses","value":"None","occurrences":"0 (0%)","score":0},{"name":"beard","value":"Brown layered beard","occurrences":"776 (7.76%)","score":"51.54639"},{"name":"hair","value":"Normal","occurrences":"0 (0%)","score":0},{"name":"helmet","value":"Iron horn threaded helmet","occurrences":"506 (5.06%)","score":"79.05138"},{"name":"antler","value":"None","occurrences":"0 (0%)","score":0},{"name":"weapon_left","value":"Twin cut blade","occurrences":"304 (3.04%)","score":"164.47368"},{"name":"weapon_right","value":"Blade short gun ","occurrences":"328 (3.28%)","score":"152.43902"}]}