{"name":"Yerrike Hbarbarian","displayName":"Yerrike Hbarbarian #03844","description":"Yerrike of Hbarbarian Club","serial":3844,"assetCID":"bafybeidkzvr4hav4h44c3nv3jvbkpsicc4txtg4bwenav6cgslrc5xw5vy","metadataCID":"bafkreighsw62ga4gmrek3mvvnayoj2qzypmkkbds7vbrsok4bzuym66d7y","rarity":1335.65638,"rank":5509,"traits":[{"name":"background","value":"Yellow horns gradient background","occurrences":"231 (2.31%)","score":"43.29004"},{"name":"back","value":"Logan sword back","occurrences":"252 (2.52%)","score":"119.04762"},{"name":"body","value":"White skin clear body","occurrences":"3588 (35.88%)","score":"5.57414"},{"name":"tattoo","value":"None","occurrences":"0 (0%)","score":0},{"name":"mouth","value":"Iguana mouth","occurrences":"287 (2.87%)","score":"69.68641"},{"name":"nose","value":"Bull's nose","occurrences":"826 (8.26%)","score":"24.21308"},{"name":"armor","value":"Ash cut armor","occurrences":"345 (3.45%)","score":"144.92754"},{"name":"chestband","value":"None","occurrences":"0 (0%)","score":0},{"name":"necklace","value":"Ghost fly necklace","occurrences":"260 (2.6%)","score":"115.38462"},{"name":"wristband","value":"Dark gry wristband","occurrences":"617 (6.17%)","score":"48.62237"},{"name":"ears","value":"Folded ears with Horn rings","occurrences":"620 (6.2%)","score":"32.25806"},{"name":"eyes","value":"Cartoon eyes","occurrences":"288 (2.88%)","score":"104.16667"},{"name":"sunglasses","value":"None","occurrences":"0 (0%)","score":0},{"name":"beard","value":"Brownies beard","occurrences":"685 (6.85%)","score":"58.39416"},{"name":"hair","value":"Normal","occurrences":"0 (0%)","score":0},{"name":"helmet","value":"Green band helmet","occurrences":"352 (3.52%)","score":"113.63636"},{"name":"antler","value":"None","occurrences":"0 (0%)","score":0},{"name":"weapon_left","value":"Arrow head blade","occurrences":"170 (1.7%)","score":"294.11765"},{"name":"weapon_right","value":"Hug blade","occurrences":"308 (3.08%)","score":"162.33766"}]}