{"name":"Ekarya Hbarbarian","displayName":"Ekarya Hbarbarian #03997","description":"Ekarya of Hbarbarian Club","serial":3997,"assetCID":"bafybeickkcltifep2ivzyxod5gpu2bhsmy22mxn7golyptmgkcignz6ism","metadataCID":"bafkreigpc6k2zgjs2pxbifevwkfws4ngugcysndzkpx2iv6sacajyljpta","rarity":31.33224,"rank":1041,"traits":[{"name":"background","value":"Red and light brown gradient background","occurrences":"234 (2.34%)","score":42.73504273504273},{"name":"back","value":"Blue cloth back","occurrences":"235 (2.35%)","score":42.5531914893617},{"name":"body","value":"White skin clear body","occurrences":"3588 (35.88%)","score":2.787068004459309},{"name":"tattoo","value":"None","occurrences":"0 (0%)","score":0},{"name":"mouth","value":"Normal","occurrences":"0 (0%)","score":0},{"name":"nose","value":"Nose with silver ring","occurrences":"1564 (15.64%)","score":6.3938618925831205},{"name":"armor","value":"G blue armor","occurrences":"367 (3.67%)","score":27.247956403269754},{"name":"chestband","value":"Hot hug chestband","occurrences":"42 (0.42%)","score":238.0952380952381},{"name":"necklace","value":"Yellow pearl necklace","occurrences":"254 (2.54%)","score":39.37007874015748},{"name":"wristband","value":"None","occurrences":"0 (0%)","score":0},{"name":"ears","value":"S cut ears with a anchor ring","occurrences":"695 (6.95%)","score":14.388489208633093},{"name":"eyes","value":"Angry pu eyes","occurrences":"190 (1.9%)","score":52.63157894736842},{"name":"sunglasses","value":"None","occurrences":"0 (0%)","score":0},{"name":"beard","value":"Brown layered beard","occurrences":"776 (7.76%)","score":12.88659793814433},{"name":"hair","value":"Normal","occurrences":"0 (0%)","score":0},{"name":"helmet","value":"Red bad pyramid helmet","occurrences":"196 (1.96%)","score":51.02040816326531},{"name":"antler","value":"None","occurrences":"0 (0%)","score":0},{"name":"weapon_left","value":"Satan's blade","occurrences":"325 (3.25%)","score":30.76923076923077},{"name":"weapon_right","value":"Ball blade","occurrences":"317 (3.17%)","score":31.545741324921135}]}