{"name":"Rillutosh Hbarbarian","displayName":"Rillutosh Hbarbarian #04192","description":"Rillutosh of Hbarbarian Club","serial":4192,"assetCID":"bafybeib6622ykjc637eji4deopcwabb3ltulltsiibka6ymkjbsycc65gm","metadataCID":"bafkreicofrbj3kspuj5wq7zyouagzz3uify4ot7swbnelphiuhrujqhbfu","rarity":1553.58018,"rank":3038,"traits":[{"name":"background","value":"Ostry gradient background","occurrences":"174 (1.74%)","score":"57.47126"},{"name":"back","value":"Logan sword back","occurrences":"252 (2.52%)","score":"119.04762"},{"name":"body","value":"White skin with hair","occurrences":"1465 (14.65%)","score":"13.65188"},{"name":"tattoo","value":"Greesco tattoo","occurrences":"125 (1.25%)","score":"240.00000"},{"name":"mouth","value":"Normal","occurrences":"0 (0%)","score":0},{"name":"nose","value":"Nose with red ring","occurrences":"1655 (16.55%)","score":"12.08459"},{"name":"armor","value":"None","occurrences":"0 (0%)","score":0},{"name":"chestband","value":"None","occurrences":"0 (0%)","score":0},{"name":"necklace","value":"Twin pearl necklace","occurrences":"235 (2.35%)","score":"127.65957"},{"name":"wristband","value":"Rainbow wristband","occurrences":"709 (7.09%)","score":"42.31312"},{"name":"ears","value":"Folded ears with pink p rings","occurrences":"291 (2.91%)","score":"68.72852"},{"name":"eyes","value":"Bowbro eyes","occurrences":"706 (7.06%)","score":"42.49292"},{"name":"sunglasses","value":"None","occurrences":"0 (0%)","score":0},{"name":"beard","value":"Long chao beard","occurrences":"595 (5.95%)","score":"67.22689"},{"name":"hair","value":"Ash cut hair","occurrences":"447 (4.47%)","score":"89.48546"},{"name":"helmet","value":"None","occurrences":"0 (0%)","score":0},{"name":"antler","value":"Leaf green antler","occurrences":"372 (3.72%)","score":"107.52688"},{"name":"weapon_left","value":"Blue flame blade","occurrences":"215 (2.15%)","score":"232.55814"},{"name":"weapon_right","value":"King's sword","occurrences":"150 (1.5%)","score":"333.33333"}]}