{"name":"Izabon Hbarbarian","displayName":"Izabon Hbarbarian #04502","description":"Izabon of Hbarbarian Club","serial":4502,"assetCID":"bafybeie7ai742lj2kz5zkbdgwi4szmci65z3tile4ap2ubuv5q36lhlg2q","metadataCID":"bafkreid3d7dhw7vj2erx76x77s2gdv7b2szowakcjl2kshseqoi5nmpybe","rarity":28.03478,"rank":1868,"traits":[{"name":"background","value":"Brown ball gradient background","occurrences":"194 (1.94%)","score":51.54639175257732},{"name":"back","value":"Back with ninja-pole","occurrences":"259 (2.59%)","score":38.61003861003861},{"name":"body","value":"Brown skin with hair","occurrences":"1416 (14.16%)","score":7.062146892655368},{"name":"tattoo","value":"T swords tattoo","occurrences":"373 (3.73%)","score":26.80965147453083},{"name":"mouth","value":"Normal","occurrences":"0 (0%)","score":0},{"name":"nose","value":"Pig's nose","occurrences":"1235 (12.35%)","score":8.097165991902834},{"name":"armor","value":"None","occurrences":"0 (0%)","score":0},{"name":"chestband","value":"Rings chestband","occurrences":"157 (1.57%)","score":63.69426751592356},{"name":"necklace","value":"Bad brown necklace","occurrences":"285 (2.85%)","score":35.08771929824562},{"name":"wristband","value":"None","occurrences":"0 (0%)","score":0},{"name":"ears","value":"S cut ears with a anchor ring","occurrences":"695 (6.95%)","score":14.388489208633093},{"name":"eyes","value":"Sad eyes","occurrences":"784 (7.84%)","score":12.755102040816327},{"name":"sunglasses","value":"Blue flat sunglasses","occurrences":"158 (1.58%)","score":63.29113924050633},{"name":"beard","value":"Popash beard","occurrences":"303 (3.03%)","score":33.00330033003301},{"name":"hair","value":"Normal","occurrences":"0 (0%)","score":0},{"name":"helmet","value":"Red band helmet","occurrences":"152 (1.52%)","score":65.78947368421052},{"name":"antler","value":"None","occurrences":"0 (0%)","score":0},{"name":"weapon_left","value":"Red band sword","occurrences":"328 (3.28%)","score":30.48780487804878},{"name":"weapon_right","value":"Horn sword","occurrences":"151 (1.51%)","score":66.2251655629139}]}