{"name":"Kyawame Hbarbarian","displayName":"Kyawame Hbarbarian #04764","description":"Kyawame of Hbarbarian Club","serial":4764,"assetCID":"bafybeicjn7uzczpvw6gubqgpwrey2xj4yaec5fvpqkdypkfd7ig2hvtcxq","metadataCID":"bafkreidwjjuayu3i262ugjl7opmoubjaecd6mudjt5h74lozxqukhf2zfy","rarity":30.14533,"rank":1275,"traits":[{"name":"background","value":"Brown art background","occurrences":"65 (0.65%)","score":153.84615384615384},{"name":"back","value":"None","occurrences":"0 (0%)","score":0},{"name":"body","value":"Brown skin clear","occurrences":"3481 (34.81%)","score":2.872737719046251},{"name":"tattoo","value":"Mid blade tattoo","occurrences":"194 (1.94%)","score":51.54639175257732},{"name":"mouth","value":"Normal","occurrences":"0 (0%)","score":0},{"name":"nose","value":"Rat's nose","occurrences":"1765 (17.65%)","score":5.665722379603399},{"name":"armor","value":"None","occurrences":"0 (0%)","score":0},{"name":"chestband","value":"Mix steel chestband","occurrences":"156 (1.56%)","score":64.1025641025641},{"name":"necklace","value":"Dora necklace","occurrences":"90 (0.9%)","score":111.11111111111111},{"name":"wristband","value":"Prince wristband","occurrences":"355 (3.55%)","score":28.169014084507044},{"name":"ears","value":"Twin ears with s hook flip ring","occurrences":"697 (6.97%)","score":14.347202295552368},{"name":"eyes","value":"Angry bat eyes","occurrences":"633 (6.33%)","score":15.797788309636651},{"name":"sunglasses","value":"None","occurrences":"0 (0%)","score":0},{"name":"beard","value":"Twinbrow beard","occurrences":"278 (2.78%)","score":35.97122302158273},{"name":"hair","value":"Normal","occurrences":"0 (0%)","score":0},{"name":"helmet","value":"Pop viking helmet","occurrences":"411 (4.11%)","score":24.330900243309003},{"name":"antler","value":"None","occurrences":"0 (0%)","score":0},{"name":"weapon_left","value":"King's sword","occurrences":"150 (1.5%)","score":66.66666666666667},{"name":"weapon_right","value":"Twin short blades","occurrences":"198 (1.98%)","score":50.505050505050505}]}