{"name":"Thinenge Hbarbarian","displayName":"Thinenge Hbarbarian #04973","description":"Thinenge of Hbarbarian Club","serial":4973,"assetCID":"bafybeiflw3xzfc3wksektl6hwedtibyxlavboagt26hqb7ht7jm2x7q5ta","metadataCID":"bafkreicavhnsugrkhcwbpcpxjpaksifkch6l3cv5fexdifiyncs5oxip4i","rarity":18.29977,"rank":8271,"traits":[{"name":"background","value":"Faid moon bambo gradient background","occurrences":"246 (2.46%)","score":40.65040650406504},{"name":"back","value":"Back with ninja-pole","occurrences":"259 (2.59%)","score":38.61003861003861},{"name":"body","value":"Brown skin with hair","occurrences":"1416 (14.16%)","score":7.062146892655368},{"name":"tattoo","value":"Byzn tattoo","occurrences":"505 (5.05%)","score":19.801980198019802},{"name":"mouth","value":"Normal","occurrences":"0 (0%)","score":0},{"name":"nose","value":"Pig's nose","occurrences":"1235 (12.35%)","score":8.097165991902834},{"name":"armor","value":"None","occurrences":"0 (0%)","score":0},{"name":"chestband","value":"None","occurrences":"0 (0%)","score":0},{"name":"necklace","value":"None","occurrences":"0 (0%)","score":0},{"name":"wristband","value":"Matyellow wristband","occurrences":"520 (5.2%)","score":19.23076923076923},{"name":"ears","value":"Monkey ears","occurrences":"614 (6.14%)","score":16.286644951140065},{"name":"eyes","value":"Sad eyes","occurrences":"784 (7.84%)","score":12.755102040816327},{"name":"sunglasses","value":"None","occurrences":"0 (0%)","score":0},{"name":"beard","value":"Hitbro beard","occurrences":"703 (7.03%)","score":14.22475106685633},{"name":"hair","value":"Black swag hair","occurrences":"481 (4.81%)","score":20.79002079002079},{"name":"helmet","value":"None","occurrences":"0 (0%)","score":0},{"name":"antler","value":"Ash cow antler","occurrences":"378 (3.78%)","score":26.455026455026456},{"name":"weapon_left","value":"Hug blade","occurrences":"308 (3.08%)","score":32.467532467532465},{"name":"weapon_right","value":"King's sword","occurrences":"150 (1.5%)","score":66.66666666666667}]}