{"name":"Etubang Hbarbarian","displayName":"Etubang Hbarbarian #05859","description":"Etubang of Hbarbarian Club","serial":5859,"assetCID":"bafybeiesbhqpix4j3bxxt4xjlns7voqvpjkcgkrau5de3qssmqxtkwmaji","metadataCID":"bafkreiheaewoig34vog5h2qgoyzapk7ondu45okzvwhgcfk6rdbiucy4xe","rarity":1041.9766,"rank":8923,"traits":[{"name":"background","value":"Unicorn bambo gradient background","occurrences":"213 (2.13%)","score":"46.94836"},{"name":"back","value":"Logan sword back","occurrences":"252 (2.52%)","score":"119.04762"},{"name":"body","value":"White skin with hair","occurrences":"1465 (14.65%)","score":"13.65188"},{"name":"tattoo","value":"Weapdrag tattoo","occurrences":"497 (4.97%)","score":"60.36217"},{"name":"mouth","value":"Normal","occurrences":"0 (0%)","score":0},{"name":"nose","value":"Nose with red ring","occurrences":"1655 (16.55%)","score":"12.08459"},{"name":"armor","value":"None","occurrences":"0 (0%)","score":0},{"name":"chestband","value":"None","occurrences":"0 (0%)","score":0},{"name":"necklace","value":"None","occurrences":"0 (0%)","score":0},{"name":"wristband","value":"Silver moon wristband","occurrences":"454 (4.54%)","score":"66.07930"},{"name":"ears","value":"Vampire ears with gold silver rings","occurrences":"501 (5.01%)","score":"39.92016"},{"name":"eyes","value":"Kind eye","occurrences":"749 (7.49%)","score":"40.05340"},{"name":"sunglasses","value":"None","occurrences":"0 (0%)","score":0},{"name":"beard","value":"Curlyking beard","occurrences":"715 (7.15%)","score":"55.94406"},{"name":"hair","value":"Red curls brown hair","occurrences":"386 (3.86%)","score":"103.62694"},{"name":"helmet","value":"None","occurrences":"0 (0%)","score":0},{"name":"antler","value":"Black line antler","occurrences":"215 (2.15%)","score":"186.04651"},{"name":"weapon_left","value":"Red band sword","occurrences":"328 (3.28%)","score":"152.43902"},{"name":"weapon_right","value":"Short hook","occurrences":"343 (3.43%)","score":"145.77259"}]}