{"name":"Phesarom Hbarbarian","displayName":"Phesarom Hbarbarian #00623","description":"Phesarom of Hbarbarian Club","serial":623,"assetCID":"bafybeicckiowozf5svk3oihtn2xgb2ufl7o2u6kbvwtfoadtut7q7zkpkq","metadataCID":"bafkreifwf3i7gmbknmyxlw77hy52asolwv252c6anbcbf5bro4ivjyo6hi","rarity":33.20541,"rank":788,"traits":[{"name":"background","value":"Light blue src gradient background","occurrences":"232 (2.32%)","score":43.10344827586207},{"name":"back","value":"None","occurrences":"0 (0%)","score":0},{"name":"body","value":"Brown skin clear","occurrences":"3481 (34.81%)","score":2.872737719046251},{"name":"tattoo","value":"None","occurrences":"0 (0%)","score":0},{"name":"mouth","value":"Normal","occurrences":"0 (0%)","score":0},{"name":"nose","value":"Pig's nose","occurrences":"1235 (12.35%)","score":8.097165991902834},{"name":"armor","value":"Pink t armor","occurrences":"204 (2.04%)","score":49.01960784313726},{"name":"chestband","value":"None","occurrences":"0 (0%)","score":0},{"name":"necklace","value":"Little horn necklace","occurrences":"98 (0.98%)","score":102.04081632653062},{"name":"wristband","value":"Matyellow wristband","occurrences":"520 (5.2%)","score":19.23076923076923},{"name":"ears","value":"Byzn ears with four rings","occurrences":"732 (7.32%)","score":13.66120218579235},{"name":"eyes","value":"Panda eyes","occurrences":"662 (6.62%)","score":15.105740181268882},{"name":"sunglasses","value":"Short blue sunglasses","occurrences":"117 (1.17%)","score":85.47008547008546},{"name":"beard","value":"Ash viking beard","occurrences":"474 (4.74%)","score":21.09704641350211},{"name":"hair","value":"Ash cut hair","occurrences":"447 (4.47%)","score":22.371364653243848},{"name":"helmet","value":"None","occurrences":"0 (0%)","score":0},{"name":"antler","value":"Orange bent antler","occurrences":"121 (1.21%)","score":82.64462809917356},{"name":"weapon_left","value":"Short hug sword","occurrences":"281 (2.81%)","score":35.587188612099645},{"name":"weapon_right","value":"Ninja blade","occurrences":"147 (1.47%)","score":68.02721088435374}]}