{"name":"Ehozim Hbarbarian","displayName":"Ehozim Hbarbarian #06266","description":"Ehozim of Hbarbarian Club","serial":6266,"assetCID":"bafybeidpgd3in5jjxvhvo5fuyagdb2p2cyol2cbsiiylu6rhv6eo47ce7e","metadataCID":"bafkreidyelfsfo46gvz7bz4fi5h6idzcj73nm7f7udvzk6ijn4oydycsha","rarity":1542.06045,"rank":3167,"traits":[{"name":"background","value":"Hashgraph nodes background","occurrences":"70 (0.7%)","score":"142.85714"},{"name":"back","value":"None","occurrences":"0 (0%)","score":0},{"name":"body","value":"White skin clear body","occurrences":"3588 (35.88%)","score":"5.57414"},{"name":"tattoo","value":"None","occurrences":"0 (0%)","score":0},{"name":"mouth","value":"Normal","occurrences":"0 (0%)","score":0},{"name":"nose","value":"Nose with silver ring","occurrences":"1564 (15.64%)","score":"12.78772"},{"name":"armor","value":"Leaf green armor","occurrences":"256 (2.56%)","score":"195.31250"},{"name":"chestband","value":"Bind fit chestband","occurrences":"141 (1.41%)","score":"212.76596"},{"name":"necklace","value":"Ghost fly necklace","occurrences":"260 (2.6%)","score":"115.38462"},{"name":"wristband","value":"None","occurrences":"0 (0%)","score":0},{"name":"ears","value":"Wolf ears","occurrences":"341 (3.41%)","score":"58.65103"},{"name":"eyes","value":"Ilumi eye","occurrences":"378 (3.78%)","score":"79.36508"},{"name":"sunglasses","value":"None","occurrences":"0 (0%)","score":0},{"name":"beard","value":"White beard","occurrences":"430 (4.3%)","score":"93.02326"},{"name":"hair","value":"Normal","occurrences":"0 (0%)","score":0},{"name":"helmet","value":"Pink pop helmet","occurrences":"529 (5.29%)","score":"75.61437"},{"name":"antler","value":"None","occurrences":"0 (0%)","score":0},{"name":"weapon_left","value":"Hook sword","occurrences":"230 (2.3%)","score":"217.39130"},{"name":"weapon_right","value":"King's sword","occurrences":"150 (1.5%)","score":"333.33333"}]}