{"name":"Phikiway Hbarbarian","displayName":"Phikiway Hbarbarian #06362","description":"Phikiway of Hbarbarian Club","serial":6362,"assetCID":"bafybeicpeotj7irsq4d2ug5obf6fo2nm7w2tao5pkwvcyqsetbarz5ktne","metadataCID":"bafkreieiidmenqehh6ofptyfuvjgbhgghb5v3r4yeoaho7dznood7vbgwq","rarity":1278.91957,"rank":6247,"traits":[{"name":"background","value":"Rainy day gradient background","occurrences":"137 (1.37%)","score":"72.99270"},{"name":"back","value":"None","occurrences":"0 (0%)","score":0},{"name":"body","value":"White skin clear body","occurrences":"3588 (35.88%)","score":"5.57414"},{"name":"tattoo","value":"None","occurrences":"0 (0%)","score":0},{"name":"mouth","value":"Normal","occurrences":"0 (0%)","score":0},{"name":"nose","value":"Rat's nose","occurrences":"1765 (17.65%)","score":"11.33144"},{"name":"armor","value":"Pink t armor","occurrences":"204 (2.04%)","score":"245.09804"},{"name":"chestband","value":"None","occurrences":"0 (0%)","score":0},{"name":"necklace","value":"Little horn necklace","occurrences":"98 (0.98%)","score":"306.12245"},{"name":"wristband","value":"Dark blue wristband","occurrences":"623 (6.23%)","score":"48.15409"},{"name":"ears","value":"Folded ears with Horn rings","occurrences":"620 (6.2%)","score":"32.25806"},{"name":"eyes","value":"Ilumi eye","occurrences":"378 (3.78%)","score":"79.36508"},{"name":"sunglasses","value":"None","occurrences":"0 (0%)","score":0},{"name":"beard","value":"Curlyking beard","occurrences":"715 (7.15%)","score":"55.94406"},{"name":"hair","value":"Normal","occurrences":"0 (0%)","score":0},{"name":"helmet","value":"Silver hook helmet","occurrences":"799 (7.99%)","score":"50.06258"},{"name":"antler","value":"None","occurrences":"0 (0%)","score":0},{"name":"weapon_left","value":"Assasin killer","occurrences":"221 (2.21%)","score":"226.24434"},{"name":"weapon_right","value":"Short hook","occurrences":"343 (3.43%)","score":"145.77259"}]}