{"name":"Ikata Hbarbarian","displayName":"Ikata Hbarbarian #07071","description":"Ikata of Hbarbarian Club","serial":7071,"assetCID":"bafybeiejhoibnga4netm3vsskhmnuerokkhxw4c6k2xr2q6jsxieb3phji","metadataCID":"bafkreiggrh6xzhrd7pbkvks5lxpludmahht22j7kyaullmh3pnugpafcfu","rarity":1128.53258,"rank":8140,"traits":[{"name":"background","value":"Sahar gradient background","occurrences":"241 (2.41%)","score":"41.49378"},{"name":"back","value":"Turtle back","occurrences":"137 (1.37%)","score":"218.97810"},{"name":"body","value":"Brown skin with hair","occurrences":"1416 (14.16%)","score":"14.12429"},{"name":"tattoo","value":"Weapdrag tattoo","occurrences":"497 (4.97%)","score":"60.36217"},{"name":"mouth","value":"Normal","occurrences":"0 (0%)","score":0},{"name":"nose","value":"Parrot's nose","occurrences":"1208 (12.08%)","score":"16.55629"},{"name":"armor","value":"None","occurrences":"0 (0%)","score":0},{"name":"chestband","value":"None","occurrences":"0 (0%)","score":0},{"name":"necklace","value":"None","occurrences":"0 (0%)","score":0},{"name":"wristband","value":"None","occurrences":"0 (0%)","score":0},{"name":"ears","value":"Bat ears","occurrences":"234 (2.34%)","score":"85.47009"},{"name":"eyes","value":"Focused eyes","occurrences":"475 (4.75%)","score":"63.15789"},{"name":"sunglasses","value":"Flower frame sunglasses","occurrences":"189 (1.89%)","score":"158.73016"},{"name":"beard","value":"White beard","occurrences":"430 (4.3%)","score":"93.02326"},{"name":"hair","value":"Normal","occurrences":"0 (0%)","score":0},{"name":"helmet","value":"Silver hook helmet","occurrences":"799 (7.99%)","score":"50.06258"},{"name":"antler","value":"None","occurrences":"0 (0%)","score":0},{"name":"weapon_left","value":"Blue ax","occurrences":"347 (3.47%)","score":"144.09222"},{"name":"weapon_right","value":"Horn blade","occurrences":"274 (2.74%)","score":"182.48175"}]}