{"name":"Kulihnay Hbarbarian","displayName":"Kulihnay Hbarbarian #07665","description":"Kulihnay of Hbarbarian Club","serial":7665,"assetCID":"bafybeibjkfhnqtn5v4noq5j5gr6dzdy5zfwzeleryruwioyt2in2rkevv4","metadataCID":"bafkreicipbfofdxaeawhcblqar7gtrq5jhu7y6zmyau5u5dsxu2c4iskny","rarity":22.76108,"rank":4840,"traits":[{"name":"background","value":"Green plant background","occurrences":"138 (1.38%)","score":72.46376811594203},{"name":"back","value":"None","occurrences":"0 (0%)","score":0},{"name":"body","value":"Brown skin clear","occurrences":"3481 (34.81%)","score":2.872737719046251},{"name":"tattoo","value":"Green arrow tattoo","occurrences":"480 (4.8%)","score":20.833333333333332},{"name":"mouth","value":"Normal","occurrences":"0 (0%)","score":0},{"name":"nose","value":"Rat's nose","occurrences":"1765 (17.65%)","score":5.665722379603399},{"name":"armor","value":"None","occurrences":"0 (0%)","score":0},{"name":"chestband","value":"None","occurrences":"0 (0%)","score":0},{"name":"necklace","value":"Shark red necklace","occurrences":"273 (2.73%)","score":36.63003663003663},{"name":"wristband","value":"Rainbow wristband","occurrences":"709 (7.09%)","score":14.104372355430183},{"name":"ears","value":"S cut ears with a anchor ring","occurrences":"695 (6.95%)","score":14.388489208633093},{"name":"eyes","value":"Super angry eyes","occurrences":"683 (6.83%)","score":14.641288433382138},{"name":"sunglasses","value":"None","occurrences":"0 (0%)","score":0},{"name":"beard","value":"Orange beard","occurrences":"462 (4.62%)","score":21.645021645021647},{"name":"hair","value":"Curly ash hair","occurrences":"148 (1.48%)","score":67.56756756756756},{"name":"helmet","value":"None","occurrences":"0 (0%)","score":0},{"name":"antler","value":"Blue dragon antler","occurrences":"239 (2.39%)","score":41.84100418410042},{"name":"weapon_left","value":"Blade long gun","occurrences":"198 (1.98%)","score":50.505050505050505},{"name":"weapon_right","value":"Drumstick","occurrences":"213 (2.13%)","score":46.948356807511736}]}