{"name":"Remegaph Hbarbarian","displayName":"Remegaph Hbarbarian #07880","description":"Remegaph of Hbarbarian Club","serial":7880,"assetCID":"bafybeierabxyqma2i5eipxeqnycowuabfb4j57kghmjtejzymtxn7o5eji","metadataCID":"bafkreihgm6tb2dzrobgrk5lqkc6ti5sd74xilhhjzoj4m62ok4n7uhcuem","rarity":20.62423,"rank":6515,"traits":[{"name":"background","value":"Weapons gradient background","occurrences":"35 (0.35%)","score":285.7142857142857},{"name":"back","value":"None","occurrences":"0 (0%)","score":0},{"name":"body","value":"Brown skin clear","occurrences":"3481 (34.81%)","score":2.872737719046251},{"name":"tattoo","value":"Tigo tattoo","occurrences":"141 (1.41%)","score":70.92198581560284},{"name":"mouth","value":"Buu buu mouth","occurrences":"201 (2.01%)","score":49.75124378109453},{"name":"nose","value":"Nose with silver ring","occurrences":"1564 (15.64%)","score":6.3938618925831205},{"name":"armor","value":"None","occurrences":"0 (0%)","score":0},{"name":"chestband","value":"None","occurrences":"0 (0%)","score":0},{"name":"necklace","value":"None","occurrences":"0 (0%)","score":0},{"name":"wristband","value":"None","occurrences":"0 (0%)","score":0},{"name":"ears","value":"Bat ears","occurrences":"234 (2.34%)","score":42.73504273504273},{"name":"eyes","value":"Panda eyes","occurrences":"662 (6.62%)","score":15.105740181268882},{"name":"sunglasses","value":"None","occurrences":"0 (0%)","score":0},{"name":"beard","value":"Brownies beard","occurrences":"685 (6.85%)","score":14.598540145985401},{"name":"hair","value":"Normal","occurrences":"0 (0%)","score":0},{"name":"helmet","value":"Pop viking helmet","occurrences":"411 (4.11%)","score":24.330900243309003},{"name":"antler","value":"None","occurrences":"0 (0%)","score":0},{"name":"weapon_left","value":"Three blades","occurrences":"256 (2.56%)","score":39.0625},{"name":"weapon_right","value":"Short pointy ax","occurrences":"313 (3.13%)","score":31.94888178913738}]}