{"name":"Gyikameng Hbarbarian","displayName":"Gyikameng Hbarbarian #09194","description":"Gyikameng of Hbarbarian Club","serial":9194,"assetCID":"bafybeihyx5t7cwowfl32t2nu5zdgpbzbyyxkrmzzj7hiyfq5bu3hc5bwzu","metadataCID":"bafkreid4d7t2zjmrdl32d4kukqgkdjnjioksx56collkgww6httfz2uvc4","rarity":19.13454,"rank":7679,"traits":[{"name":"background","value":"Silverball gradient background","occurrences":"194 (1.94%)","score":51.54639175257732},{"name":"back","value":"None","occurrences":"0 (0%)","score":0},{"name":"body","value":"White skin clear body","occurrences":"3588 (35.88%)","score":2.787068004459309},{"name":"tattoo","value":"Redhot tattoo","occurrences":"399 (3.99%)","score":25.06265664160401},{"name":"mouth","value":"Normal","occurrences":"0 (0%)","score":0},{"name":"nose","value":"Nose with red ring","occurrences":"1655 (16.55%)","score":6.042296072507553},{"name":"armor","value":"None","occurrences":"0 (0%)","score":0},{"name":"chestband","value":"None","occurrences":"0 (0%)","score":0},{"name":"necklace","value":"Binder necklace","occurrences":"165 (1.65%)","score":60.60606060606061},{"name":"wristband","value":"Twin bro wristband","occurrences":"225 (2.25%)","score":44.44444444444444},{"name":"ears","value":"S cut ears with a anchor ring","occurrences":"695 (6.95%)","score":14.388489208633093},{"name":"eyes","value":"Side eyes","occurrences":"667 (6.67%)","score":14.992503748125937},{"name":"sunglasses","value":"Lite orange sunglasses","occurrences":"220 (2.2%)","score":45.45454545454545},{"name":"beard","value":"Brownies beard","occurrences":"685 (6.85%)","score":14.598540145985401},{"name":"hair","value":"Normal","occurrences":"0 (0%)","score":0},{"name":"helmet","value":"Green band helmet","occurrences":"352 (3.52%)","score":28.40909090909091},{"name":"antler","value":"None","occurrences":"0 (0%)","score":0},{"name":"weapon_left","value":"Side hook blade","occurrences":"298 (2.98%)","score":33.557046979865774},{"name":"weapon_right","value":"Twin blade","occurrences":"317 (3.17%)","score":31.545741324921135}]}