{"name":"Leforu Hbarbarian","displayName":"Leforu Hbarbarian #09617","description":"Leforu of Hbarbarian Club","serial":9617,"assetCID":"bafybeigwor6dlt4ujwv4rx4mwl6zlpq7tvznvtnvgosq7q7vlcel4dabfy","metadataCID":"bafkreic632yoqtn47fwdipil6znca4b6xr73wrsa5f3x726i7dzzaajyg4","rarity":1070.56972,"rank":8711,"traits":[{"name":"background","value":"Green plant background","occurrences":"138 (1.38%)","score":"72.46377"},{"name":"back","value":"None","occurrences":"0 (0%)","score":0},{"name":"body","value":"Brown skin clear","occurrences":"3481 (34.81%)","score":"5.74548"},{"name":"tattoo","value":"None","occurrences":"0 (0%)","score":0},{"name":"mouth","value":"Normal","occurrences":"0 (0%)","score":0},{"name":"nose","value":"Rat's nose","occurrences":"1765 (17.65%)","score":"11.33144"},{"name":"armor","value":"Green t armor","occurrences":"367 (3.67%)","score":"136.23978"},{"name":"chestband","value":"None","occurrences":"0 (0%)","score":0},{"name":"necklace","value":"Binder necklace","occurrences":"165 (1.65%)","score":"181.81818"},{"name":"wristband","value":"Matyellow wristband","occurrences":"520 (5.2%)","score":"57.69231"},{"name":"ears","value":"Twin ears with s hook flip ring","occurrences":"697 (6.97%)","score":"28.69440"},{"name":"eyes","value":"Panda eyes","occurrences":"662 (6.62%)","score":"45.31722"},{"name":"sunglasses","value":"None","occurrences":"0 (0%)","score":0},{"name":"beard","value":"Lbrown beard","occurrences":"680 (6.8%)","score":"58.82353"},{"name":"hair","value":"Normal","occurrences":"0 (0%)","score":0},{"name":"helmet","value":"Pop viking helmet","occurrences":"411 (4.11%)","score":"97.32360"},{"name":"antler","value":"None","occurrences":"0 (0%)","score":0},{"name":"weapon_left","value":"Hook sword","occurrences":"230 (2.3%)","score":"217.39130"},{"name":"weapon_right","value":"Ball blade","occurrences":"317 (3.17%)","score":"157.72871"}]}